musika.py
musika-1.2.6.dist-info/licenses/LICENSE
musika-1.2.6.dist-info/METADATA
musika-1.2.6.dist-info/WHEEL
musika-1.2.6.dist-info/entry_points.txt
musika-1.2.6.dist-info/top_level.txt
musika-1.2.6.dist-info/RECORD
