Metadata-Version: 2.4
Name: musika
Version: 1.2.6
Summary: Minimal command-line music player written in Python
Author: Julynx
License: GPL-2.0-only
Project-URL: Homepage, https://github.com/Julynx/musika
Project-URL: Repository, https://github.com/Julynx/musika
Requires-Python: <3.14,>=3.11
License-File: LICENSE
Requires-Dist: cursor>=1.3.5
Requires-Dist: mutagen>=1.47.0
Requires-Dist: pygame>=2.6.1
Requires-Dist: pynput>=1.8.1
Dynamic: license-file
